nimbleway_webit/__init__.py
nimbleway_webit/_base_client.py
nimbleway_webit/_client.py
nimbleway_webit/_compat.py
nimbleway_webit/_constants.py
nimbleway_webit/_exceptions.py
nimbleway_webit/_files.py
nimbleway_webit/_models.py
nimbleway_webit/_qs.py
nimbleway_webit/_resource.py
nimbleway_webit/_response.py
nimbleway_webit/_streaming.py
nimbleway_webit/_types.py
nimbleway_webit/_version.py
nimbleway_webit/py.typed
nimbleway_webit/_utils/__init__.py
nimbleway_webit/_utils/_compat.py
nimbleway_webit/_utils/_datetime_parse.py
nimbleway_webit/_utils/_logs.py
nimbleway_webit/_utils/_proxy.py
nimbleway_webit/_utils/_reflection.py
nimbleway_webit/_utils/_resources_proxy.py
nimbleway_webit/_utils/_streams.py
nimbleway_webit/_utils/_sync.py
nimbleway_webit/_utils/_transform.py
nimbleway_webit/_utils/_typing.py
nimbleway_webit/_utils/_utils.py
nimbleway_webit/lib/.keep
nimbleway_webit/resources/__init__.py
nimbleway_webit/resources/v2/__init__.py
nimbleway_webit/resources/v2/crawl.py
nimbleway_webit/resources/v2/v2.py
nimbleway_webit/types/__init__.py
nimbleway_webit/types/v2_extract_params.py
nimbleway_webit/types/v2_extract_response.py
nimbleway_webit/types/v2_extract_template_params.py
nimbleway_webit/types/v2_extract_template_response.py
nimbleway_webit/types/v2_map_params.py
nimbleway_webit/types/v2_map_response.py
nimbleway_webit/types/v2/__init__.py
nimbleway_webit/types/v2/crawl_cancel_response.py
nimbleway_webit/types/v2/crawl_crawl_params.py
nimbleway_webit/types/v2/crawl_crawl_response.py
nimbleway_webit/types/v2/crawl_get_response.py
nimbleway_webit/types/v2/crawl_list_params.py
nimbleway_webit/types/v2/crawl_list_response.py
nimbleway_webit-0.0.3.dist-info/METADATA
nimbleway_webit-0.0.3.dist-info/WHEEL
nimbleway_webit-0.0.3.dist-info/licenses/LICENSE
nimbleway_webit-0.0.3.dist-info/RECORD
